<?xml version="1.0" encoding="utf-8"?>
<tt ttp:contentProfiles="http://www.w3.org/ns/ttml/profile/imsc1.1/text" xmlns="http://www.w3.org/ns/ttml" xmlns:nttm="http://www.netflix.com/ns/ttml#metadata" xmlns:tt="http://www.w3.org/ns/ttml" xmlns:ttp="http://www.w3.org/ns/ttml#parameter" xmlns:tts="http://www.w3.org/ns/ttml#styling" xmlns:xml="http://www.w3.org/XML/1998/namespace" ttp:tickRate="10000000" ttp:timeBase="media" xml:lang="ko">
<head>
<metadata nttm:movieID="80178585" nttm:packageID="1354212" nttm:schemaVersion="0" nttm:textType="CC" nttm:uuid="329f93b5-c044-4695-b5c2-ee6d1c3c9a2c"/>
<styling>
<initial tts:backgroundColor="transparent" tts:color="white" tts:displayAlign="after" tts:extent="80.000% 80.000%" tts:fontSize="6.000rh" tts:opacity="1.000" tts:origin="10.000% 10.000%" tts:showBackground="whenActive" tts:textAlign="center" tts:textOutline="black 0.300rh" tts:writingMode="lrtb"/>
<style xml:id="style0" tts:fontWeight="normal"/>
</styling>
<layout>
<region xml:id="region0" tts:displayAlign="after" tts:extent="80.000% 80.000%" tts:origin="10.000% 10.000%"/>
<region xml:id="region1" tts:displayAlign="before" tts:extent="80.000% 80.000%" tts:origin="10.000% 10.000%"/>
</layout>
</head>
<body>
<div>
<p xml:id="subtitle1" begin="62395666t" end="112779333t" region="region0" style="style0">&quot;NETFLIX<br/>오리지널 시리즈&quot;</p>
<p xml:id="subtitle2" begin="136803333t" end="166833333t" region="region0" style="style0">[주제곡]</p>
<p xml:id="subtitle3" begin="725057666t" end="742074666t" region="region0" style="style0">온달을 살릴 수만 있다면</p>
<p xml:id="subtitle4" begin="765431333t" end="773773000t" region="region0" style="style0">죽어도 괜찮아</p>
<p xml:id="subtitle5" begin="774440333t" end="787787000t" region="region0" style="style0">[잔잔한 음악]<br/>누나</p>
<p xml:id="subtitle6" begin="807473333t" end="820820000t" region="region0" style="style0">(내비게이션)<br/>곧 출발합니다</p>
<p xml:id="subtitle7" begin="821487333t" end="836502333t" region="region0" style="style0">[자동차 시동음]</p>
<p xml:id="subtitle8" begin="838170666t" end="856856000t" region="region0" style="style0">- (삼용) 세트장? 지금?<br/>- (수정) 어?</p>
<p xml:id="subtitle9" begin="861527333t" end="875207666t" region="region0" style="style0">아, 안 돼<br/>[삼용의 거친 숨소리]</p>
<p xml:id="subtitle10" begin="877209666t" end="894226666t" region="region0" style="style0">- (수정) 어, 어?<br/>- (삼용) 어, 어?</p>
<p xml:id="subtitle11" begin="901901000t" end="914246666t" region="region0" style="style0">(수정)<br/>안 돼!<br/>[차 문이 탁 잠긴다]</p>
<p xml:id="subtitle12" begin="916248666t" end="933265666t" region="region0" style="style0">- (삼용) 뭐야?<br/>- (수정) 어?</p>
<p xml:id="subtitle13" begin="1175841333t" end="1186518666t" region="region0" style="style0">[놀라는 숨소리]</p>
<p xml:id="subtitle14" begin="1193192000t" end="1202534666t" region="region0" style="style0">온달?</p>
<p xml:id="subtitle15" begin="1213212000t" end="1223555666t" region="region0" style="style0">난년아</p>
<p xml:id="subtitle16" begin="1239905333t" end="1251917333t" region="region0" style="style0">[칼이 푹 꽂힌다]<br/>[놀라는 신음]</p>
<p xml:id="subtitle17" begin="1253252000t" end="1263595666t" region="region0" style="style0">안 돼!</p>
<p xml:id="subtitle18" begin="1275941333t" end="1286285000t" region="region0" style="style0">[칼을 쓱 뺀다]</p>
<p xml:id="subtitle19" begin="1287286000t" end="1298964333t" region="region0" style="style0">[신음]</p>
<p xml:id="subtitle20" begin="1335334000t" end="1345677666t" region="region0" style="style0">돌아가야 돼</p>
<p xml:id="subtitle21" begin="1346345000t" end="1358023333t" region="region0" style="style0">[울부짖으며]<br/>안 돼!</p>
<p xml:id="subtitle22" begin="1358690666t" end="1379044333t" region="region0" style="style0">[수정이 흐느낀다]</p>
<p xml:id="subtitle23" begin="1723388333t" end="1742741000t" region="region0" style="style0">(내비게이션)<br/>종착지에 도착했습니다</p>
<p xml:id="subtitle24" begin="1746077666t" end="1756087666t" region="region0" style="style0">종착지?</p>
<p xml:id="subtitle25" begin="1767432333t" end="1781112666t" region="region0" style="style0">[다급한 숨소리]</p>
<p xml:id="subtitle26" begin="1783114666t" end="1791456333t" region="region0" style="style0">어?</p>
<p xml:id="subtitle27" begin="1826157666t" end="1836501333t" region="region0" style="style0">[한숨]</p>
<p xml:id="subtitle28" begin="1846845000t" end="1860525333t" region="region0" style="style0">돌아와 버렸어</p>
<p xml:id="subtitle29" begin="1875874000t" end="1887886000t" region="region0" style="style0">[수정의 거친 숨소리]</p>
<p xml:id="subtitle30" begin="1892890999t" end="1916581333t" region="region0" style="style0">[거친 숨을 내뱉으며]<br/>아니야</p>
<p xml:id="subtitle31" begin="1920251666t" end="1928593333t" region="region0" style="style0">꿈</p>
<p xml:id="subtitle32" begin="1937602333t" end="1949614333t" region="region0" style="style0">꿈이어야 돼</p>
<p xml:id="subtitle33" begin="1985650333t" end="1997662333t" region="region0" style="style0">[차 문을 탁탁 두드린다]</p>
<p xml:id="subtitle34" begin="2012343666t" end="2029694333t" region="region0" style="style0">(조감독)<br/>아, 여기 있으면 어떡해요</p>
<p xml:id="subtitle35" begin="2038703333t" end="2049046999t" region="region0" style="style0">(삼용)<br/>여기가 어, 어디예요?</p>
<p xml:id="subtitle36" begin="2049714333t" end="2066397666t" region="region0" style="style0">어디긴 어디야, 세트장이지</p>
<p xml:id="subtitle37" begin="2070735333t" end="2082747333t" region="region0" style="style0">(조감독)<br/>아, 빨리 준비하세요, 네?</p>
<p xml:id="subtitle38" begin="2083414666t" end="2098763333t" region="region0" style="style0">아, 다 기다리고 있잖아요, 지금</p>
<p xml:id="subtitle39" begin="2099430666t" end="2114445666t" region="region0" style="style0">기다려? 누가?</p>
<p xml:id="subtitle40" begin="2123121000t" end="2133464666t" region="region0" style="style0">아이, 저기</p>
<p xml:id="subtitle41" begin="2135466666t" end="2148813333t" region="region0" style="style0">감독님하고 스태프들이요</p>
<p xml:id="subtitle42" begin="2156154000t" end="2167832333t" region="region0" style="style0">얼른 준비하세요, 네?</p>
<p xml:id="subtitle43" begin="2168499666t" end="2185516666t" region="region0" style="style0">[뛰어가는 발걸음]</p>
<p xml:id="subtitle44" begin="2213878333t" end="2223888333t" region="region0" style="style0">돌아온 거야?</p>
<p xml:id="subtitle45" begin="2299297000t" end="2307638666t" region="region0" style="style0">(삼용)<br/>어?</p>
<p xml:id="subtitle46" begin="2308306000t" end="2321652666t" region="region0" style="style0">- (감독) 야, 조감독!<br/>- (조감독) 예</p>
<p xml:id="subtitle47" begin="2322320000t" end="2333331000t" region="region0" style="style0">(감독)<br/>야, 수정 씨 뭐 해, 인마</p>
<p xml:id="subtitle48" begin="2333998333t" end="2348012333t" region="region0" style="style0">(조감독)<br/>예, 다 왔습니다<br/>[감독이 재촉한다]</p>
<p xml:id="subtitle49" begin="2348679666t" end="2361359000t" region="region0" style="style0">예, 송수정 씨 오셨습니다</p>
<p xml:id="subtitle50" begin="2363027333t" end="2373037333t" region="region0" style="style0">자, 자, 자, 자</p>
<p xml:id="subtitle51" begin="2375039333t" end="2395726666t" region="region0" style="style0">자, 됐습니다<br/>자, 슛 들어갑니다</p>
<p xml:id="subtitle52" begin="2408406000t" end="2429093333t" region="region0" style="style0">(삼용)<br/>아이, 뭐야, 이거?</p>
<p xml:id="subtitle53" begin="2466464000t" end="2491822666t" region="region0" style="style0">삼용아, 수정이 컨디션 괜찮냐?</p>
<p xml:id="subtitle54" begin="2509507000t" end="2526524000t" region="region0" style="style0">어? 대, 대표님</p>
<p xml:id="subtitle55" begin="2529527000t" end="2539870666t" region="region0" style="style0">(삼용)<br/>대표님</p>
<p xml:id="subtitle56" begin="2555886666t" end="2564228333t" region="region0" style="style0">(대표)<br/>왜 그래?</p>
<p xml:id="subtitle57" begin="2564895666t" end="2579910666t" region="region0" style="style0">(삼용)<br/>보고 싶었어요</p>
<p xml:id="subtitle58" begin="2596927666t" end="2625623000t" region="region0" style="style0">(대표)<br/>10분 전에 봤잖아<br/>요즘 왜 이러니, 진짜</p>
<p xml:id="subtitle59" begin="2643641000t" end="2661992666t" region="region0" style="style0">수정이 쟤, 들었니?</p>
<p xml:id="subtitle60" begin="2666997666t" end="2684348333t" region="region0" style="style0">너 탈탈 털디?</p>
<p xml:id="subtitle61" begin="2692690000t" end="2712042666t" region="region0" style="style0">아이, 뭐, 뭘, 뭘 들어요?</p>
<p xml:id="subtitle62" begin="2722386333t" end="2734064666t" region="region0" style="style0">배다른 여동생</p>
<p xml:id="subtitle63" begin="2737401333t" end="2749079666t" region="region0" style="style0">배다른 여동생?</p>
<p xml:id="subtitle64" begin="2758088666t" end="2778108666t" region="region0" style="style0">[흥미진진한 음악]</p>
<p xml:id="subtitle65" begin="2779777000t" end="2807137666t" region="region0" style="style0">[삼용의 놀라는 숨소리]<br/>(감독)<br/>맞아, 배다른 동생</p>
<p xml:id="subtitle66" begin="2811475333t" end="2828492333t" region="region0" style="style0">송수정 씨, 이미진이에요</p>
<p xml:id="subtitle67" begin="2829159666t" end="2841171666t" region="region0" style="style0">와, 이<br/>[음소거 효과음]<br/>발</p>
<p xml:id="subtitle68" begin="2841839000t" end="2860858000t" region="region0" style="style0">(수정)<br/>이 콩만도 못한 새끼가 뒤지려고<br/>새끼야</p>
<p xml:id="subtitle69" begin="2861525333t" end="2871535333t" region="region0" style="style0">(감독)<br/>아, 하지 마</p>
<p xml:id="subtitle70" begin="2872202666t" end="2883881000t" region="region0" style="style0">야, 이<br/>[음소거 효과음]<br/>어디 가냐!</p>
<p xml:id="subtitle71" begin="2884548333t" end="2893557333t" region="region0" style="style0">(수정)<br/>아씨, 귀싸대기를...</p>
<p xml:id="subtitle72" begin="2894224666t" end="2911575333t" region="region0" style="style0">야, 니 엔지 내고, 이 새끼가</p>
<p xml:id="subtitle73" begin="2912242666t" end="2946276666t" region="region0" style="style0">뭘 봐, 이 새끼들아<br/>완전 현장 이거 개판이네, 진짜</p>
<p xml:id="subtitle74" begin="2951949000t" end="2963627333t" region="region0" style="style0">[놀라는 숨소리]</p>
<p xml:id="subtitle75" begin="2976640333t" end="2986983999t" region="region0" style="style0">그 날로</p>
<p xml:id="subtitle76" begin="2993991000t" end="3005002000t" region="region0" style="style0">돌아왔다?</p>
<p xml:id="subtitle77" begin="3008338666t" end="3018682333t" region="region0" style="style0">삼용아</p>
<p xml:id="subtitle78" begin="3025355666t" end="3038702333t" region="region0" style="style0">나 여기 없는 거다, 어?</p>
<p xml:id="subtitle79" begin="3041038000t" end="3066063000t" region="region0" style="style0">저기, 수정이 저렇게 누그러지면<br/>그때 불러, 알았지?</p>
<p xml:id="subtitle80" begin="3070400666t" end="3084081000t" region="region0" style="style0">아이, 아이, 저기, 저, 잠깐만</p>
<p xml:id="subtitle81" begin="3084748333t" end="3094758333t" region="region0" style="style0">(삼용)<br/>아이...</p>
<p xml:id="subtitle82" begin="3104101000t" end="3116113000t" region="region0" style="style0">아, 대표님</p>
<p xml:id="subtitle83" begin="3131461666t" end="3147477666t" region="region0" style="style0">아이씨, 어떡해</p>
<p xml:id="subtitle84" begin="3152149000t" end="3162492666t" region="region0" style="style0">[당황하는 숨소리]</p>
<p xml:id="subtitle85" begin="3163160000t" end="3179843333t" region="region0" style="style0">(감독)<br/>자, 자, 시간 없어, 빨리 가자</p>
<p xml:id="subtitle86" begin="3184848333t" end="3194858333t" region="region0" style="style0">자, 레디</p>
<p xml:id="subtitle87" begin="3201198000t" end="3209539666t" region="region0" style="style0">액션!</p>
<p xml:id="subtitle88" begin="3210207000t" end="3237234000t" region="region0" style="style0">[웅장한 음악]</p>
<p xml:id="subtitle89" begin="3286616666t" end="3297294000t" region="region0" style="style0">(수정)<br/>아바마마?</p>
<p xml:id="subtitle90" begin="3303300000t" end="3316646666t" region="region0" style="style0">오냐, 그래</p>
<p xml:id="subtitle91" begin="3332996333t" end="3355018333t" region="region0" style="style0">아바마마께서 항상 말씀하시기를</p>
<p xml:id="subtitle92" begin="3361691666t" end="3377040333t" region="region0" style="style0">너는 반드시 온달...</p>
<p xml:id="subtitle93" begin="3398395000t" end="3408405000t" region="region0" style="style0">온달</p>
<p xml:id="subtitle94" begin="3423086333t" end="3436433000t" region="region0" style="style0">어떻게 됐지?</p>
<p xml:id="subtitle95" begin="3447777666t" end="3459456000t" region="region0" style="style0">[헛기침]</p>
<p xml:id="subtitle96" begin="3462792666t" end="3479809666t" region="region0" style="style0">온달이 어떻게 됐는지는</p>
<p xml:id="subtitle97" begin="3484147333t" end="3494491000t" region="region0" style="style0">나는 모르지</p>
<p xml:id="subtitle98" begin="3496826666t" end="3505502000t" region="region0" style="style0">(감독)<br/>컷!</p>
<p xml:id="subtitle99" begin="3506169333t" end="3517847666t" region="region0" style="style0">아, '모르지'가 어디 있어<br/>'모르지'가</p>
<p xml:id="subtitle100" begin="3518515000t" end="3535198333t" region="region0" style="style0">- 이러고 있을 때가 아니야<br/>- (감독) 아이, 정말</p>
<p xml:id="subtitle101" begin="3541871666t" end="3567230333t" region="region0" style="style0">(감독)<br/>아유, 수정 씨, 다 좋았는데</p>
<p xml:id="subtitle102" begin="3569899666t" end="3593256333t" region="region0" style="style0">또 뭐가 마음에 안 드나, 어?<br/>아니, 지금 봐 봐라</p>
<p xml:id="subtitle103" begin="3593923666t" end="3613610000t" region="region0" style="style0">우리 지금 다들<br/>세 시간 넘게 기다리고 있었는데</p>
<p xml:id="subtitle104" begin="3614944666t" end="3623620000t" region="region0" style="style0">사또</p>
<p xml:id="subtitle105" begin="3625955666t" end="3637633999t" region="region0" style="style0">- 비켜<br/>- 어?</p>
<p xml:id="subtitle106" begin="3641971666t" end="3650647000t" region="region0" style="style0">사또?</p>
<p xml:id="subtitle107" begin="3651314333t" end="3666996666t" region="region0" style="style0">딱 봐도 탐관오리처럼 생겨 가지고</p>
<p xml:id="subtitle108" begin="3667664000t" end="3681010666t" region="region0" style="style0">[익살스러운 음악]<br/>오리?</p>
<p xml:id="subtitle109" begin="3681678000t" end="3702031666t" region="region0" style="style0">[오리 울음 효과음]</p>
<p xml:id="subtitle110" begin="3707370333t" end="3723386333t" region="region0" style="style0">딱 봐도 얍실한 이방이고</p>
<p xml:id="subtitle111" begin="3724053666t" end="3736399333t" region="region0" style="style0">[익살스러운 효과음]<br/>네?</p>
<p xml:id="subtitle112" begin="3737733999t" end="3751748000t" region="region0" style="style0">아, 저 내관인데요</p>
<p xml:id="subtitle113" begin="3755084666t" end="3770099666t" region="region0" style="style0">(수정)<br/>둘이 아주 잘 어울린다</p>
<p xml:id="subtitle114" begin="3770767000t" end="3781110666t" region="region0" style="style0">(감독)<br/>아이...</p>
<p xml:id="subtitle115" begin="3785448333t" end="3797460333t" region="region0" style="style0">연기를 이방처럼 하니까, 이씨</p>
<p xml:id="subtitle116" begin="3798127666t" end="3818147666t" region="region0" style="style0">어이, 수정 씨<br/>수정 씨, 수정 씨!</p>
<p xml:id="subtitle117" begin="3818815000t" end="3832161666t" region="region0" style="style0">(내시)<br/>아, 저, 감, 감독님</p>
<p xml:id="subtitle118" begin="3834497333t" end="3856519333t" region="region0" style="style0">저 이방 시켜 주십시오<br/>자신 있습니다</p>
<p xml:id="subtitle119" begin="3857186666t" end="3869198666t" region="region0" style="style0">[내시의 웃음]</p>
<p xml:id="subtitle120" begin="3874537333t" end="3904901000t" region="region0" style="style0">이야, 쟤 진짜 노답이다</p>
<p xml:id="subtitle121" begin="3910239666t" end="3920917000t" region="region0" style="style0">(미진)<br/>송수정 씨</p>
<p xml:id="subtitle122" begin="3926923000t" end="3945608333t" region="region0" style="style0">- 이미진이...<br/>- 돈밖에 없는 마마보이</p>
<p xml:id="subtitle123" begin="3948611333t" end="3956953000t" region="region0" style="style0">너 가져</p>
<p xml:id="subtitle124" begin="3957620333t" end="3972635333t" region="region0" style="style0">(미진)<br/>[기가 찬 숨을 내뱉으며]<br/>잠시만요</p>
<p xml:id="subtitle125" begin="3993656333t" end="4004333666t" region="region0" style="style0">(수정)<br/>잡지 말지?</p>
<p xml:id="subtitle126" begin="4014677333t" end="4023018999t" region="region0" style="style0">(미진)<br/>잠깐 논 거...</p>
<p xml:id="subtitle127" begin="4023686333t" end="4037366666t" region="region0" style="style0">(수정)<br/>이해할 수 있는 거 알고</p>
<p xml:id="subtitle128" begin="4040703333t" end="4049378666t" region="region0" style="style0">(미진)<br/>오빠랑 급이 안...</p>
<p xml:id="subtitle129" begin="4050046000t" end="4073736333t" region="region0" style="style0">(수정)<br/>안 맞지, 내 급이 워낙 높으니까</p>
<p xml:id="subtitle130" begin="4076405666t" end="4091754333t" region="region0" style="style0">그러니까 너 가지라고</p>
<p xml:id="subtitle131" begin="4092421666t" end="4114110000t" region="region0" style="style0">(미진)<br/>[피식하며]<br/>주제 파악이 안 되나 본데...</p>
<p xml:id="subtitle132" begin="4114777333t" end="4130126000t" region="region0" style="style0">(수정)<br/>잘하니까 너 가지라는 거야</p>
<p xml:id="subtitle133" begin="4140136000t" end="4162158000t" region="region0" style="style0">아, 걔 엉덩이 맞는 거 좋아한다</p>
<p xml:id="subtitle134" begin="4169165000t" end="4182845333t" region="region0" style="style0">행복하게 잘 살아</p>
<p xml:id="subtitle135" begin="4187516666t" end="4203866333t" region="region0" style="style0">(미진)<br/>[기가 찬 숨을 내뱉으며]<br/>너 이게 진짜</p>
<p xml:id="subtitle136" begin="4204533666t" end="4224553666t" region="region0" style="style0">[흥미진진한 음악]</p>
<p xml:id="subtitle137" begin="4278607666t" end="4297293000t" region="region0" style="style0">[수정의 기합]</p>
<p xml:id="subtitle138" begin="4297960333t" end="4309638666t" region="region0" style="style0">[미진의 신음]</p>
<p xml:id="subtitle139" begin="4314643666t" end="4326655666t" region="region0" style="style0">[까마귀 울음 효과음]</p>
<p xml:id="subtitle140" begin="4327323000t" end="4340669666t" region="region0" style="style0">- (대표) 수정아<br/>- (수정) 놔요</p>
<p xml:id="subtitle141" begin="4341337000t" end="4356685666t" region="region0" style="style0">(삼용)<br/>아, 이게 뭐야, 진짜</p>
<p xml:id="subtitle142" begin="4357353000t" end="4377706666t" region="region0" style="style0">[삼용과 대표의 신음]</p>
<p xml:id="subtitle143" begin="4413075333t" end="4421417000t" region="region0" style="style0">(대표)<br/>응?</p>
<p xml:id="subtitle144" begin="4422418000t" end="4432428000t" region="region0" style="style0">보고 싶었어</p>
<p xml:id="subtitle145" begin="4433095333t" end="4466462000t" region="region0" style="style0">[멋쩍게 웃으며]<br/>저, 수, 수, 수정아<br/>저, 무, 무, 무섭다</p>
<p xml:id="subtitle146" begin="4479475000t" end="4489485000t" region="region0" style="style0">이제 놔</p>
<p xml:id="subtitle147" begin="4490486000t" end="4501163333t" region="region0" style="style0">(대표)<br/>아, 안 돼! 씨</p>
<p xml:id="subtitle148" begin="4501830666t" end="4520849666t" region="region0" style="style0">- (대표) 아휴, 야, 수정아<br/>- (수정) 아, 좀 놓으라고</p>
<p xml:id="subtitle149" begin="4521517000t" end="4529858666t" region="region0" style="style0">(대표)<br/>안 돼</p>
<p xml:id="subtitle150" begin="4530859666t" end="4554550000t" region="region0" style="style0">[익살스러운 음악]<br/>수정아, 내가 다 처리할게, 어?</p>
<p xml:id="subtitle151" begin="4555884666t" end="4573235333t" region="region0" style="style0">그리고 스태프들 입도 막고<br/>다 할 테니까</p>
<p xml:id="subtitle152" begin="4574903666t" end="4596925666t" region="region0" style="style0">집 말고 회사 말고<br/>사람들 아는 데 말고, 어?</p>
<p xml:id="subtitle153" begin="4597593000t" end="4621283333t" region="region0" style="style0">삼용이랑 아무도 모르는 데<br/>먼 데 가 있어, 어?</p>
<p xml:id="subtitle154" begin="4628290333t" end="4636965666t" region="region0" style="style0">(수정)<br/>어</p>
<p xml:id="subtitle155" begin="4638634000t" end="4650312333t" region="region0" style="style0">- (수정) 그다음에<br/>- (대표) 뭐?</p>
<p xml:id="subtitle156" begin="4650979666t" end="4660989666t" region="region0" style="style0">- (수정) 빨리<br/>- (대표) 어?</p>
<p xml:id="subtitle157" begin="4661657000t" end="4679675000t" region="region0" style="style0">아, 하려고 했던 말<br/>빨리 하라고요!</p>
<p xml:id="subtitle158" begin="4680676000t" end="4696024666t" region="region0" style="style0">내가? 그, 그, 그, 그게</p>
<p xml:id="subtitle159" begin="4696692000t" end="4720716000t" region="region0" style="style0">어어, 그래, 그래<br/>내가 다 처리할 테니까</p>
<p xml:id="subtitle160" begin="4721383333t" end="4751747000t" region="region0" style="style0">(대표)<br/>삼용이랑 아무, 아무도<br/>모르는 데, 먼 데 가 있어</p>
<p xml:id="subtitle161" begin="4755417333t" end="4765761000t" region="region0" style="style0">오케이</p>
<p xml:id="subtitle162" begin="4768764000t" end="4777439333t" region="region0" style="style0">무사 삼용</p>
<p xml:id="subtitle163" begin="4778106666t" end="4791787000t" region="region0" style="style0">명 받들겠습니다</p>
<p xml:id="subtitle164" begin="4797125666t" end="4804800000t" region="region0" style="style0">가자</p>
<p xml:id="subtitle165" begin="4839167666t" end="4852848000t" region="region0" style="style0">쟤들 뭐야?</p>
<p xml:id="subtitle166" begin="4872534333t" end="4889885000t" region="region0" style="style0">회사 밴 놔두고 저 차는 왜 타?</p>
<p xml:id="subtitle167" begin="4901897000t" end="4910238666t" region="region0" style="style0">(수정)<br/>어</p>
<p xml:id="subtitle168" begin="4911573333t" end="4931593333t" region="region0" style="style0">이, 이, 이, 이, 이다음에<br/>어떻게 했더라?</p>
<p xml:id="subtitle169" begin="4932260666t" end="4943939000t" region="region0" style="style0">[손뼉을 탁 치며]<br/>시동, 시동, 시동</p>
<p xml:id="subtitle170" begin="4944606333t" end="4961289666t" region="region0" style="style0">아, 시동</p>
<p xml:id="subtitle171" begin="4968296666t" end="4984980000t" region="region0" style="style0">[자동차 시동음]<br/>어, 걸렸고</p>
<p xml:id="subtitle172" begin="4985981000t" end="4999661333t" region="region0" style="style0">(수정)<br/>이, 이, 이다음에는?</p>
<p xml:id="subtitle173" begin="5016344666t" end="5028356666t" region="region0" style="style0">어, 어디로 가지?</p>
<p xml:id="subtitle174" begin="5029024000t" end="5048376666t" region="region0" style="style0">(내비게이션)<br/>목적지가 설정되었습니다</p>
<p xml:id="subtitle175" begin="5049711333t" end="5058053000t" region="region0" style="style0">어?</p>
<p xml:id="subtitle176" begin="5058720333t" end="5068730333t" region="region0" style="style0">(내비게이션)<br/>우회전</p>
<p xml:id="subtitle177" begin="5069397666t" end="5079741333t" region="region0" style="style0">우회전?</p>
<p xml:id="subtitle178" begin="5087415666t" end="5109437666t" region="region1" style="style0">(내비게이션)<br/>지금 당장 우회전하십시오</p>
<p xml:id="subtitle179" begin="5134129000t" end="5147475666t" region="region0" style="style0">내비가 알아서 했어</p>
<p xml:id="subtitle180" begin="5165493666t" end="5182177000t" region="region0" style="style0">아, 이거 아무것도 안 하는데요?</p>
<p xml:id="subtitle181" begin="5190852333t" end="5200862333t" region="region0" style="style0">안 돼</p>
<p xml:id="subtitle182" begin="5211206000t" end="5231559666t" region="region0" style="style0">[다급하게]<br/>설정해, 아, 빨리</p>
<p xml:id="subtitle183" begin="5238900333t" end="5249244000t" region="region0" style="style0">[한숨]</p>
<p xml:id="subtitle184" begin="5268596666t" end="5279274000t" region="region0" style="style0">부탁할게</p>
<p xml:id="subtitle185" begin="5295957333t" end="5316311000t" region="region0" style="style0">온달 칼 맞는 거 봤단 말이야</p>
<p xml:id="subtitle186" begin="5329657666t" end="5343671666t" region="region0" style="style0">(수정)<br/>죽었을지도 몰라</p>
<p xml:id="subtitle187" begin="5355683666t" end="5365693666t" region="region0" style="style0">제발</p>
<p xml:id="subtitle188" begin="5374702666t" end="5388049333t" region="region0" style="style0">제발 부탁할게</p>
<p xml:id="subtitle189" begin="5425753666t" end="5436097333t" region="region0" style="style0">누나...</p>
<p xml:id="subtitle190" begin="5463124333t" end="5471799666t" region="region0" style="style0">어?</p>
<p xml:id="subtitle191" begin="5472467000t" end="5481142333t" region="region0" style="style0">&quot;역사&quot;</p>
<p xml:id="subtitle192" begin="5481809666t" end="5495490000t" region="region0" style="style0">누나, 책</p>
<p xml:id="subtitle193" begin="5505500000t" end="5515843666t" region="region0" style="style0">(수정)<br/>책?</p>
<p xml:id="subtitle194" begin="5543537999t" end="5553881666t" region="region0" style="style0">(삼용)<br/>어?</p>
<p xml:id="subtitle195" begin="5559220333t" end="5574235333t" region="region0" style="style0">주, 죽었어?</p>
<p xml:id="subtitle196" begin="5576571000t" end="5603264333t" region="region0" style="style0">아니, 그, 그, 그게<br/>그게 아니라</p>
<p xml:id="subtitle197" begin="5620615000t" end="5637298333t" region="region0" style="style0">[신비한 효과음]</p>
<p xml:id="subtitle198" begin="5645640000t" end="5655650000t" region="region0" style="style0">(수정)<br/>어?</p>
<p xml:id="subtitle199" begin="5685680000t" end="5695690000t" region="region0" style="style0">안 돼</p>
<p xml:id="subtitle200" begin="5713708000t" end="5730725000t" region="region0" style="style0">온달<br/>[온달의 신음]</p>
<p xml:id="subtitle201" begin="5733394333t" end="5760087666t" region="region0" style="style0">[박진감 넘치는 음악]<br/>[온달의 가쁜 숨소리]</p>
<p xml:id="subtitle202" begin="5787448333t" end="5802797000t" region="region0" style="style0">[칼이 바람을 쉭 가른다]</p>
<p xml:id="subtitle203" begin="5826153666t" end="5837832000t" region="region0" style="style0">[일용의 기합]</p>
<p xml:id="subtitle204" begin="5863858000t" end="5877872000t" region="region0" style="style0">(온달)<br/>일 합!<br/>[칼이 푹 꽂힌다]</p>
<p xml:id="subtitle205" begin="5898225666t" end="5918579333t" region="region0" style="style0">이것은 9살의 네가 죽인</p>
<p xml:id="subtitle206" begin="5923584333t" end="5940601333t" region="region0" style="style0">내 아버지를 위함이다</p>
<p xml:id="subtitle207" begin="5946607333t" end="5966961000t" region="region0" style="style0">[칼을 쓱 뽑는다]<br/>[일용의 신음]</p>
<p xml:id="subtitle208" begin="5971298666t" end="5988649333t" region="region0" style="style0">이 합!<br/>[일용의 신음]</p>
<p xml:id="subtitle209" begin="5997658333t" end="6018012000t" region="region0" style="style0">[거친 숨소리]</p>
<p xml:id="subtitle210" begin="6018679333t" end="6037364666t" region="region0" style="style0">15년간 네가 죽인</p>
<p xml:id="subtitle211" begin="6049710333t" end="6065059000t" region="region0" style="style0">사람들을 위함이오</p>
<p xml:id="subtitle212" begin="6076403666t" end="6096423666t" region="region0" style="style0">[신음]</p>
<p xml:id="subtitle213" begin="6099760333t" end="6113107000t" region="region0" style="style0">삼 합!<br/>[일용의 신음]</p>
<p xml:id="subtitle214" begin="6131458666t" end="6148475666t" region="region0" style="style0">[일용의 신음]<br/>[일용이 털썩 쓰러진다]</p>
<p xml:id="subtitle215" begin="6169830333t" end="6187181000t" region="region0" style="style0">앞으로 네가 죽였을</p>
<p xml:id="subtitle216" begin="6202863333t" end="6216877333t" region="region0" style="style0">사람들을 위해서다</p>
<p xml:id="subtitle217" begin="6231558666t" end="6251578666t" region="region0" style="style0">[거친 숨소리]</p>
<p xml:id="subtitle218" begin="6282609666t" end="6297958333t" region="region0" style="style0">꽃 같은 내가</p>
<p xml:id="subtitle219" begin="6312306000t" end="6322316000t" region="region0" style="style0">죽...</p>
<p xml:id="subtitle220" begin="6476470000t" end="6486813666t" region="region0" style="style0">(온달)<br/>무명!</p>
<p xml:id="subtitle221" begin="6493153333t" end="6506833666t" region="region0" style="style0">눈을 떠라, 무명</p>
<p xml:id="subtitle222" begin="6550210333t" end="6561888666t" region="region0" style="style0">마마의 이름을</p>
<p xml:id="subtitle223" begin="6569896666t" end="6586913666t" region="region0" style="style0">마마께 불러 드려야지</p>
<p xml:id="subtitle224" begin="6597591000t" end="6607601000t" region="region0" style="style0">평강</p>
<p xml:id="subtitle225" begin="6621281333t" end="6636296333t" region="region0" style="style0">평강, 그 이름을...</p>
<p xml:id="subtitle226" begin="6652646000t" end="6664324333t" region="region0" style="style0">무명</p>
<p xml:id="subtitle227" begin="6675001666t" end="6685345333t" region="region0" style="style0">평강</p>
<p xml:id="subtitle228" begin="6745405333t" end="6772098666t" region="region0" style="style0">[무명의 아파하는 신음]</p>
<p xml:id="subtitle229" begin="6965625333t" end="6989315666t" region="region0" style="style0">[슬픈 음악]</p>
<p xml:id="subtitle230" begin="7013673333t" end="7043703333t" region="region0" style="style0">[훌쩍인다]<br/>[흐느낀다]</p>
<p xml:id="subtitle231" begin="7052712333t" end="7063056000t" region="region0" style="style0">무명</p>
<p xml:id="subtitle232" begin="7112105000t" end="7134127000t" region="region0" style="style0">[관이 달칵 열린다]</p>
<p xml:id="subtitle233" begin="7186846333t" end="7206532666t" region="region0" style="style0">[웅장한 음악]</p>
<p xml:id="subtitle234" begin="7338998333t" end="7363022333t" region="region0" style="style0">(상선)<br/>폐하와 저를 제외한<br/>세상 모든 이에게</p>
<p xml:id="subtitle235" begin="7368694666t" end="7389048333t" region="region0" style="style0">두 분은 죽은 것으로<br/>되어 있습니다</p>
<p xml:id="subtitle236" begin="7397056333t" end="7410403000t" region="region0" style="style0">고일용의 잔당들이</p>
<p xml:id="subtitle237" begin="7413406000t" end="7433759666t" region="region0" style="style0">언제 어떻게 두 분을 노릴지 몰라</p>
<p xml:id="subtitle238" begin="7435094333t" end="7449108333t" region="region0" style="style0">그리 두는 게 좋을 듯하니</p>
<p xml:id="subtitle239" begin="7453446000t" end="7480473000t" region="region0" style="style0">송구스럽지만 궐에 도착할 때까지</p>
<p xml:id="subtitle240" begin="7489815666t" end="7508167333t" region="region0" style="style0">관 안에 들어가 계셔야 합니다</p>
<p xml:id="subtitle241" begin="7512838666t" end="7529522000t" region="region0" style="style0">나는 돌아가지 않습니다</p>
<p xml:id="subtitle242" begin="7544870666t" end="7562221333t" region="region0" style="style0">난년이가 사라져 버린 궐로</p>
<p xml:id="subtitle243" begin="7589248333t" end="7604263333t" region="region0" style="style0">돌아갈 이유가 없지요</p>
<p xml:id="subtitle244" begin="7610936666t" end="7637630000t" region="region0" style="style0">[슬픈 음악]</p>
<p xml:id="subtitle245" begin="7667660000t" end="7681340333t" region="region0" style="style0">폐하께 청이 있습니다</p>
<p xml:id="subtitle246" begin="7698023666t" end="7709702000t" region="region0" style="style0">아니, 먼저</p>
<p xml:id="subtitle247" begin="7739398333t" end="7756081666t" region="region0" style="style0">자네가 내 뜻을 받아 주게</p>
<p xml:id="subtitle248" begin="7785110666t" end="7802795000t" region="region0" style="style0">내 이름을 자네에게 주고 싶네</p>
<p xml:id="subtitle249" begin="7835828000t" end="7850842999t" region="region0" style="style0">나 대신 온달이 되어</p>
<p xml:id="subtitle250" begin="7875200666t" end="7888547333t" region="region0" style="style0">마마와 혼인해 주게</p>
<p xml:id="subtitle251" begin="8579237333t" end="8589914666t" region="region0" style="style0">무명</p>
<p xml:id="subtitle252" begin="8596921666t" end="8607265333t" region="region0" style="style0">평강</p>
<p xml:id="subtitle253" begin="8686010666t" end="8698022666t" region="region0" style="style0">연모합니다</p>
<p xml:id="subtitle254" begin="8996988000t" end="9009667333t" region="region0" style="style0">돌아왔으니 됐어</p>
<p xml:id="subtitle255" begin="9076067000t" end="9096420666t" region="region0" style="style0">[흐느낀다]</p>
<p xml:id="subtitle256" begin="9101425666t" end="9113104000t" region="region0" style="style0">잘됐어</p>
<p xml:id="subtitle257" begin="9166157000t" end="9177835333t" region="region0" style="style0">(수정)<br/>잘됐어</p>
<p xml:id="subtitle258" begin="9253244000t" end="9279937333t" region="region0" style="style0">[수정이 흐느낀다]</p>
<p xml:id="subtitle259" begin="9310968333t" end="9321645666t" region="region0" style="style0">온달</p>
<p xml:id="subtitle260" begin="9345002333t" end="9362019333t" region="region0" style="style0">[옅은 한숨]</p>
<p xml:id="subtitle261" begin="9379370000t" end="9389380000t" region="region0" style="style0">누나</p>
<p xml:id="subtitle262" begin="9401058333t" end="9418409000t" region="region0" style="style0">[수정이 흐느낀다]</p>
<p xml:id="subtitle263" begin="9438429000t" end="9449106333t" region="region0" style="style0">형님</p>
<p xml:id="subtitle264" begin="9539863666t" end="9563220333t" region="region0" style="style0">(장물아비)<br/>강국으로 가는 배는<br/>지금 없을 텐데</p>
<p xml:id="subtitle265" begin="9571228333t" end="9588245333t" region="region0" style="style0">대한민국으로 가 보려고 합니다</p>
<p xml:id="subtitle266" begin="9594918666t" end="9616607000t" region="region0" style="style0">모두 그런 나라는 없다고<br/>하지 않느냐</p>
<p xml:id="subtitle267" begin="9617274333t" end="9634291333t" region="region0" style="style0">거긴 갈 수가 없다니까, 온달아</p>
<p xml:id="subtitle268" begin="9638295333t" end="9648972666t" region="region0" style="style0">혹시 압니까?</p>
<p xml:id="subtitle269" begin="9657981666t" end="9674665000t" region="region0" style="style0">걷고 또 걷다 보면</p>
<p xml:id="subtitle270" begin="9692349333t" end="9706029666t" region="region0" style="style0">언젠가 닿을 수 있을지도</p>
<p xml:id="subtitle271" begin="9719376333t" end="9731054666t" region="region0" style="style0">온달아</p>
<p xml:id="subtitle272" begin="9747404333t" end="9759082666t" region="region0" style="style0">[옅은 숨을 내뱉는다]</p>
<p xml:id="subtitle273" begin="9817474333t" end="9848171666t" region="region0" style="style0">(수정)<br/>♪ 사랑은 조금씩 ♪</p>
<p xml:id="subtitle274" begin="9860183666t" end="9882205666t" region="region0" style="style0">♪ 내게 다가와 ♪</p>
<p xml:id="subtitle275" begin="9899556333t" end="9956613333t" region="region0" style="style0">♪ 반쪽일 뿐인 날<br/>채워 주네요 ♪</p>
<p xml:id="subtitle276" begin="9965288666t" end="9980303666t" region="region0" style="style0">♪ 떨리는 ♪</p>
<p xml:id="subtitle277" begin="9990647333t" end="10031021000t" region="region0" style="style0">♪ 마음으로 그댈 보아요 ♪</p>
<p xml:id="subtitle278" begin="10046369666t" end="10069726333t" region="region0" style="style0">♪ 소리 없이 ♪</p>
<p xml:id="subtitle279" begin="10079736333t" end="10119109000t" region="region0" style="style0">♪ 두 눈이 원하고 있죠 ♪</p>
<p xml:id="subtitle280" begin="10119776333t" end="10146469666t" region="region0" style="style0">[애잔한 음악]</p>
<p xml:id="subtitle281" begin="10982638333t" end="10993315666t" region="region0" style="style0">사랑해</p>
<p xml:id="subtitle282" begin="11092081000t" end="11109098000t" region="region0" style="style0">[슬픈 숨을 들이켠다]</p>
<p xml:id="subtitle283" begin="11282938333t" end="11297953333t" region="region0" style="style0">(대표)<br/>야, 아니</p>
<p xml:id="subtitle284" begin="11301623666t" end="11325647666t" region="region0" style="style0">외제 차 아니면 안 된다고<br/>난장 칠 때는 언제고</p>
<p xml:id="subtitle285" begin="11326315000t" end="11339661666t" region="region0" style="style0">이런 똥차를 타고...</p>
<p xml:id="subtitle286" begin="11341663666t" end="11356678666t" region="region0" style="style0">[수정과 삼용의 웃음]</p>
<p xml:id="subtitle287" begin="11358680666t" end="11382037333t" region="region0" style="style0">(삼용)<br/>이 드라마<br/>촬영해도 괜찮겠어요, 누나?</p>
<p xml:id="subtitle288" begin="11387042333t" end="11397719666t" region="region0" style="style0">(수정)<br/>그럼 안 해?</p>
<p xml:id="subtitle289" begin="11399721666t" end="11416071333t" region="region0" style="style0">내가 달고 있는 혹이 몇인데</p>
<p xml:id="subtitle290" begin="11455110333t" end="11471793666t" region="region0" style="style0">(대표)<br/>아휴<br/>[차 문이 드르륵 열린다]</p>
<p xml:id="subtitle291" begin="11487809666t" end="11499821666t" region="region0" style="style0">[차 문이 탁 닫힌다]</p>
<p xml:id="subtitle292" begin="11553208333t" end="11576898666t" region="region0" style="style0">아이, 누나도 참<br/>[삼용의 웃음]</p>
<p xml:id="subtitle293" begin="11579234333t" end="11591246333t" region="region0" style="style0">그런 말 듣고도</p>
<p xml:id="subtitle294" begin="11597252333t" end="11607596000t" region="region0" style="style0">웃음이 나오냐?</p>
<p xml:id="subtitle295" begin="11611933666t" end="11648970666t" region="region0" style="style0">산전수전 다 겪은 사이라<br/>가슴으로 이해하는 거죠</p>
<p xml:id="subtitle296" begin="11649638000t" end="11683672000t" region="region0" style="style0">아이고, 두 번 이해했다가는<br/>딴 세상 가겠다</p>
<p xml:id="subtitle297" begin="11687342333t" end="11697686000t" region="region0" style="style0">딴 세상?</p>
<p xml:id="subtitle298" begin="11713368333t" end="11730385333t" region="region0" style="style0">[한숨 쉬며]<br/>가고 싶다</p>
<p xml:id="subtitle299" begin="11738059666t" end="11753408333t" region="region0" style="style0">보고 싶어 죽겠는데</p>
<p xml:id="subtitle300" begin="11757078666t" end="11770759000t" region="region0" style="style0">요즘 너희 둘</p>
<p xml:id="subtitle301" begin="11778433333t" end="11793448333t" region="region0" style="style0">진짜 이상해</p>
<p xml:id="subtitle302" begin="11801456333t" end="11813468333t" region="region0" style="style0">[삼용의 웃음]</p>
<p xml:id="subtitle303" begin="11815804000t" end="11843164666t" region="region0" style="style0">대표님은 모르는<br/>아픔이 있어서 그래요</p>
<p xml:id="subtitle304" begin="11843832000t" end="11853842000t" region="region0" style="style0">이씨</p>
<p xml:id="subtitle305" begin="11878533333t" end="11898553333t" region="region0" style="style0">그, 이번에 새로 뽑은 매니저<br/>곧 올 거야</p>
<p xml:id="subtitle306" begin="11899220666t" end="11912900999t" region="region0" style="style0">- 여자예요?<br/>- 에이그, 저</p>
<p xml:id="subtitle307" begin="11923912000t" end="11934255666t" region="region0" style="style0">[작은 소리로]<br/>죄송합니다</p>
<p xml:id="subtitle308" begin="11934923000t" end="11951940000t" region="region0" style="style0">- 정신 줄 꽉 잡고<br/>- 네</p>
<p xml:id="subtitle309" begin="11952607333t" end="11968623333t" region="region0" style="style0">- 교육 제대로 시켜<br/>- 예</p>
<p xml:id="subtitle310" begin="11970625333t" end="11984305666t" region="region0" style="style0">[삼용의 기합]</p>
<p xml:id="subtitle311" begin="11987642333t" end="12004325666t" region="region0" style="style0">- 간다<br/>- 예, 가십시오</p>
<p xml:id="subtitle312" begin="12027682333t" end="12039360666t" region="region0" style="style0">[한숨]</p>
<p xml:id="subtitle313" begin="12078733333t" end="12090411666t" region="region0" style="style0">[한숨]</p>
<p xml:id="subtitle314" begin="12118439666t" end="12128783333t" region="region0" style="style0">[피식]</p>
<p xml:id="subtitle315" begin="12133121000t" end="12144799333t" region="region0" style="style0">보고 싶다</p>
<p xml:id="subtitle316" begin="12160815333t" end="12171159000t" region="region0" style="style0">낭자</p>
<p xml:id="subtitle317" begin="12183838333t" end="12197518666t" region="region0" style="style0">[옅은 한숨]<br/>[자동차 알림음]</p>
<p xml:id="subtitle318" begin="12205526666t" end="12215870333t" region="region0" style="style0">(삼용)<br/>어?</p>
<p xml:id="subtitle319" begin="12216871333t" end="12230551666t" region="region0" style="style0">붕붕아, 왜 그래?</p>
<p xml:id="subtitle320" begin="12236891333t" end="12247568666t" region="region0" style="style0">어디 아파?</p>
<p xml:id="subtitle321" begin="12254909333t" end="12266587666t" region="region0" style="style0">야, 아이...</p>
<p xml:id="subtitle322" begin="12267255000t" end="12280935333t" region="region0" style="style0">[다가오는 발걸음]</p>
<p xml:id="subtitle323" begin="12330318000t" end="12347001333t" region="region0" style="style0">[발랄한 음악]<br/>변삼용 씨?</p>
<p xml:id="subtitle324" begin="12349003333t" end="12359347000t" region="region0" style="style0">낭자</p>
<p xml:id="subtitle325" begin="12402390000t" end="12412400000t" region="region0" style="style0">네?</p>
<p xml:id="subtitle326" begin="12424078333t" end="12437425000t" region="region0" style="style0">[웃음]</p>
<p xml:id="subtitle327" begin="12443097333t" end="12453441000t" region="region0" style="style0">(삼용)<br/>보고 싶었어요</p>
<p xml:id="subtitle328" begin="12454108333t" end="12470791666t" region="region0" style="style0">(신입)<br/>아이씨, 이런 미친</p>
<p xml:id="subtitle329" begin="12471459000t" end="12488142333t" region="region0" style="style0">[퍽 때린다]<br/>[삼용의 신음]</p>
<p xml:id="subtitle330" begin="12498486000t" end="12515169333t" region="region0" style="style0">[익살스러운 효과음]<br/>[아파하는 신음]</p>
<p xml:id="subtitle331" begin="12528182333t" end="12540194333t" region="region0" style="style0">아, 잠깐만</p>
<p xml:id="subtitle332" begin="12556877666t" end="12584238333t" region="region0" style="style0">[아파하는 신음]</p>
<p xml:id="subtitle333" begin="12686674000t" end="12704024666t" region="region0" style="style0">앞으로는 조심하십시오</p>
<p xml:id="subtitle334" begin="12727381333t" end="12737725000t" region="region0" style="style0">네</p>
<p xml:id="subtitle335" begin="12815469333t" end="12828815999t" region="region0" style="style0">[신음]</p>
<p xml:id="subtitle336" begin="12831485333t" end="12846500333t" region="region0" style="style0">아, 차가워, 아이</p>
<p xml:id="subtitle337" begin="12879533333t" end="12896216666t" region="region0" style="style0">[요구르트를 쪽 빤다]</p>
<p xml:id="subtitle338" begin="12919573333t" end="12933253666t" region="region0" style="style0">빤히 보지 마요</p>
<p xml:id="subtitle339" begin="12933921000t" end="12944264666t" region="region0" style="style0">네</p>
<p xml:id="subtitle340" begin="12949603333t" end="12961615333t" region="region0" style="style0">[코를 훌쩍인다]</p>
<p xml:id="subtitle341" begin="12993647333t" end="13004324666t" region="region0" style="style0">그래도</p>
<p xml:id="subtitle342" begin="13020674333t" end="13037357666t" region="region0" style="style0">곁에는 있어도 되겠습니까?</p>
<p xml:id="subtitle343" begin="13049703333t" end="13067054000t" region="region0" style="style0">- 네?<br/>- 매니저 변삼용</p>
<p xml:id="subtitle344" begin="13080067000t" end="13097084000t" region="region0" style="style0">이번에는 꼭 그리하고 싶습니다</p>
<p xml:id="subtitle345" begin="13163483666t" end="13176830333t" region="region0" style="style0">잘 부탁합니다</p>
<p xml:id="subtitle346" begin="13240227000t" end="13250237000t" region="region0" style="style0">[피식]</p>
<p xml:id="subtitle347" begin="13294948333t" end="13306626666t" region="region0" style="style0">[웃음]</p>
<p xml:id="subtitle348" begin="13324311000t" end="13334988333t" region="region0" style="style0">[웃음]</p>
<p xml:id="subtitle349" begin="13359346000t" end="13371024333t" region="region0" style="style0">괜찮아요?</p>
<p xml:id="subtitle350" begin="13376363000t" end="13385038333t" region="region0" style="style0">아파요</p>
<p xml:id="subtitle351" begin="13406726666t" end="13423410000t" region="region0" style="style0">(감독)<br/>아이고, 쌀쌀하네</p>
<p xml:id="subtitle352" begin="13425745666t" end="13434421000t" region="region0" style="style0">어?</p>
<p xml:id="subtitle353" begin="13436089333t" end="13454440999t" region="region0" style="style0">아이, 왜 이렇게 일찍 왔노?</p>
<p xml:id="subtitle354" begin="13456776666t" end="13467454000t" region="region0" style="style0">답지 않게 말이죠?</p>
<p xml:id="subtitle355" begin="13468121333t" end="13487474000t" region="region0" style="style0">에이, 그런 뜻이 아이고</p>
<p xml:id="subtitle356" begin="13491144333t" end="13501488000t" region="region0" style="style0">뭐, 이렇게 좀</p>
<p xml:id="subtitle357" begin="13504491000t" end="13533186333t" region="region0" style="style0">일찍 와 줘서 고맙다<br/>뭐, 그런 뜻이지</p>
<p xml:id="subtitle358" begin="13539859666t" end="13573226333t" region="region0" style="style0">(감독)<br/>아니, 근데 혹시<br/>귀신도 막 보이고 그러나?</p>
<p xml:id="subtitle359" begin="13575895666t" end="13604591000t" region="region0" style="style0">아니, 내가 좀 께름칙해 가지고<br/>알아보니까</p>
<p xml:id="subtitle360" begin="13609929666t" end="13623276333t" region="region0" style="style0">그, 우리 조상 중에</p>
<p xml:id="subtitle361" begin="13625945666t" end="13645965666t" region="region0" style="style0">그, 단양에서<br/>사또 한 양반이 있는데</p>
<p xml:id="subtitle362" begin="13646633000t" end="13668321333t" region="region0" style="style0">이야, 이 양반이<br/>완전히 노답인 거라</p>
<p xml:id="subtitle363" begin="13674661000t" end="13688341333t" region="region0" style="style0">묘비명에, 응?</p>
<p xml:id="subtitle364" begin="13690677000t" end="13712365333t" region="region0" style="style0">탐관오리라고 딱 적혀 있더라니까</p>
<p xml:id="subtitle365" begin="13713032666t" end="13733386333t" region="region0" style="style0">[익살스러운 음악]<br/>완전히 귀신이네<br/>그거 우찌 알았지?</p>
<p xml:id="subtitle366" begin="13749736000t" end="13778431333t" region="region0" style="style0">저, 혹시 지금 내 뒤에 계시나?</p>
<p xml:id="subtitle367" begin="13779432333t" end="13789775999t" region="region0" style="style0">[피식]</p>
<p xml:id="subtitle368" begin="13793446333t" end="13802789000t" region="region0" style="style0">아니요</p>
<p xml:id="subtitle369" begin="13808795000t" end="13818805000t" region="region0" style="style0">딱 여기 있어요</p>
<p xml:id="subtitle370" begin="13819472333t" end="13829482333t" region="region0" style="style0">어?</p>
<p xml:id="subtitle371" begin="13840493333t" end="13848835000t" region="region0" style="style0">[웃음]</p>
<p xml:id="subtitle372" begin="13850837000t" end="13862515333t" region="region0" style="style0">차에서 쉬고 있을게요</p>
<p xml:id="subtitle373" begin="13863182666t" end="13883536333t" region="region0" style="style0">어어, 편하게 쉬고 있어<br/>[감독의 웃음]</p>
<p xml:id="subtitle374" begin="13910229666t" end="13923910000t" region="region0" style="style0">우리 드라마 대박은</p>
<p xml:id="subtitle375" begin="13924577333t" end="13954607333t" region="region0" style="style0">대한민국 톱스타<br/>송수정 어깨에 달려 있데이</p>
<p xml:id="subtitle376" begin="13957610333t" end="13968287666t" region="region0" style="style0">수정 씨, 알제?</p>
<p xml:id="subtitle377" begin="13970623333t" end="13982635333t" region="region0" style="style0">평강, 그녀는</p>
<p xml:id="subtitle378" begin="13984303666t" end="14018337666t" region="region0" style="style0">남자가 여자를 선택하는<br/>그런 시대적 환경을 거부하고</p>
<p xml:id="subtitle379" begin="14020673333t" end="14071057000t" region="region0" style="style0">평강 스스로 바보 온달이라는<br/>사내를 골라서 자기 인생을 개척한</p>
<p xml:id="subtitle380" begin="14071724333t" end="14108761333t" region="region0" style="style0">우리나라 역사상<br/>최초의 난년이데이!</p>
<p xml:id="subtitle381" begin="14171824333t" end="14182501666t" region="region0" style="style0">[한숨]</p>
<p xml:id="subtitle382" begin="14212198000t" end="14235554666t" region="region0" style="style0">[아련한 음악]</p>
<p xml:id="subtitle383" begin="14236222000t" end="14246232000t" region="region0" style="style0">[피식]</p>
<p xml:id="subtitle384" begin="14253239000t" end="14263582666t" region="region0" style="style0">난년?</p>
<p xml:id="subtitle385" begin="14280599666t" end="14290943333t" region="region0" style="style0">(온달)<br/>난년아</p>
<p xml:id="subtitle386" begin="14298951333t" end="14308961333t" region="region0" style="style0">난년아</p>
<p xml:id="subtitle387" begin="14309628666t" end="14319972333t" region="region0" style="style0">(수정)<br/>미쳤나 봐</p>
<p xml:id="subtitle388" begin="14320639666t" end="14332651666t" region="region0" style="style0">우리 톱스타 난년이</p>
<p xml:id="subtitle389" begin="14342995333t" end="14356675666t" region="region0" style="style0">(온달)<br/>놓치지 않을 거예요</p>
<p xml:id="subtitle390" begin="14363682666t" end="14374360000t" region="region0" style="style0">잡았다</p>
<p xml:id="subtitle391" begin="14381033333t" end="14389375000t" region="region0" style="style0">응?</p>
<p xml:id="subtitle392" begin="14390709666t" end="14401720666t" region="region0" style="style0">내가 너 잡았다고</p>
<p xml:id="subtitle393" begin="14409061333t" end="14422408000t" region="region0" style="style0">(온달)<br/>어휴, 내 팔자야</p>
<p xml:id="subtitle394" begin="14431417000t" end="14448767666t" region="region0" style="style0">난년이 이거를 만나 가지고<br/>내가 미쳐 가지고</p>
<p xml:id="subtitle395" begin="14449435000t" end="14464783666t" region="region0" style="style0">미치게 해서 미안하다</p>
<p xml:id="subtitle396" begin="14465451000t" end="14486138333t" region="region0" style="style0">온달, 잘 살아</p>
<p xml:id="subtitle397" begin="14488807666t" end="14512498000t" region="region0" style="style0">다시는 나 같은 년 만나지 말고</p>
<p xml:id="subtitle398" begin="14513165333t" end="14546532000t" region="region0" style="style0">허, 난년아<br/>우리 다시 잘 지내보자</p>
<p xml:id="subtitle399" begin="14547199333t" end="14572224333t" region="region0" style="style0">(수정)<br/>인생 폭망하면 그때 생각해 볼게</p>
<p xml:id="subtitle400" begin="14572891666t" end="14583235333t" region="region0" style="style0">난년아</p>
<p xml:id="subtitle401" begin="14596248333t" end="14608260333t" region="region0" style="style0">정신 차려</p>
<p xml:id="subtitle402" begin="14616602000t" end="14626612000t" region="region0" style="style0">(온달)<br/>우리 둘</p>
<p xml:id="subtitle403" begin="14634953666t" end="14646632000t" region="region0" style="style0">그딴 거 없어</p>
<p xml:id="subtitle404" begin="14647299333t" end="14657643000t" region="region0" style="style0">죽어도</p>
<p xml:id="subtitle405" begin="14667653000t" end="14684336333t" region="region0" style="style0">너랑 엮일 일 없을 거야</p>
<p xml:id="subtitle406" begin="14698016666t" end="14708026666t" region="region0" style="style0">죽어도</p>
<p xml:id="subtitle407" begin="14717703000t" end="14735053666t" region="region0" style="style0">아, 내 가슴도 너 때문에 시꺼메</p>
<p xml:id="subtitle408" begin="14735721000t" end="14755741000t" region="region0" style="style0">(수정)<br/>왜? 네 가슴은 네가 알아서 해</p>
<p xml:id="subtitle409" begin="14756408333t" end="14771423333t" region="region0" style="style0">이런 난년이 같은 것</p>
<p xml:id="subtitle410" begin="14773091666t" end="14795113666t" region="region0" style="style0">(온달)<br/>넌 어쩌면 그렇게 아무것도 모르니</p>
<p xml:id="subtitle411" begin="14813131666t" end="14831483333t" region="region0" style="style0">내가 너 좋아하는 거 모르지?</p>
<p xml:id="subtitle412" begin="14838824000t" end="14859177666t" region="region0" style="style0">네가 날 좋아하는 건 모르겠는데</p>
<p xml:id="subtitle413" begin="14880532333t" end="14893879000t" region="region0" style="style0">내가 널 좋아하는 건</p>
<p xml:id="subtitle414" begin="14921907000t" end="14931917000t" region="region0" style="style0">이제 알아</p>
<p xml:id="subtitle415" begin="14949935000t" end="14967285666t" region="region0" style="style0">(온달)<br/>아마 우리는<br/>내일쯤 싸우게 되겠지?</p>
<p xml:id="subtitle416" begin="14977963000t" end="14996648333t" region="region0" style="style0">네 난년이 같은 성격 때문에</p>
<p xml:id="subtitle417" begin="15002320666t" end="15019004000t" region="region0" style="style0">울컥 치밀어 오를 때가 많거든</p>
<p xml:id="subtitle418" begin="15026011000t" end="15034686333t" region="region0" style="style0">(수정)<br/>야</p>
<p xml:id="subtitle419" begin="15035353666t" end="15047365666t" region="region0" style="style0">(온달)<br/>넌 그렇게 화를 낼 거야</p>
<p xml:id="subtitle420" begin="15052704333t" end="15066718333t" region="region0" style="style0">와, 큰일 났다</p>
<p xml:id="subtitle421" begin="15069721333t" end="15100085000t" region="region0" style="style0">나는 아차 싶어서<br/>너를 어떻게 풀어 줄까 고민하다가</p>
<p xml:id="subtitle422" begin="15126111000t" end="15141125999t" region="region0" style="style0">이런 걸 준비하게 될 거야</p>
<p xml:id="subtitle423" begin="15160145000t" end="15170488666t" region="region0" style="style0">용서해 줘</p>
<p xml:id="subtitle424" begin="15175493666t" end="15192510666t" region="region0" style="style0">삼용이처럼 네 세상에</p>
<p xml:id="subtitle425" begin="15199517666t" end="15214532666t" region="region0" style="style0">너도 가족들이 있겠지?</p>
<p xml:id="subtitle426" begin="15220872333t" end="15249234000t" region="region0" style="style0">그런데 널 잡는다, 내가</p>
<p xml:id="subtitle427" begin="15278596666t" end="15290608666t" region="region0" style="style0">정말 미안해</p>
<p xml:id="subtitle428" begin="15303621666t" end="15313965333t" region="region0" style="style0">하지만</p>
<p xml:id="subtitle429" begin="15341993333t" end="15359010333t" region="region0" style="style0">반드시 행복하게 해 주마</p>
<p xml:id="subtitle430" begin="15380698666t" end="15394379000t" region="region0" style="style0">네가 사는 세상과</p>
<p xml:id="subtitle431" begin="15412730666t" end="15426077333t" region="region0" style="style0">내가 사는 세상</p>
<p xml:id="subtitle432" begin="15460111333t" end="15477128333t" region="region0" style="style0">그 어떤 여인들보다 더</p>
<p xml:id="subtitle433" begin="15482467000t" end="15494479000t" region="region0" style="style0">그러니 난년아</p>
<p xml:id="subtitle434" begin="15500818666t" end="15514499000t" region="region0" style="style0">나와 혼인해 주겠니?</p>
<p xml:id="subtitle435" begin="15533184333t" end="15541526000t" region="region0" style="style0">응</p>
<p xml:id="subtitle436" begin="15554872666t" end="15565216333t" region="region0" style="style0">(수정)<br/>안 돼</p>
<p xml:id="subtitle437" begin="15572223333t" end="15585570000t" region="region0" style="style0">가면 죽어</p>
<p xml:id="subtitle438" begin="15590908666t" end="15601919666t" region="region0" style="style0">인사는 안 한다</p>
<p xml:id="subtitle439" begin="15629614000t" end="15641292333t" region="region0" style="style0">우린 꼭</p>
<p xml:id="subtitle440" begin="15668986666t" end="15682333333t" region="region0" style="style0">다시 만날 거니까</p>
<p xml:id="subtitle441" begin="15772757000t" end="15782767000t" region="region0" style="style0">온달</p>
<p xml:id="subtitle442" begin="16068385666t" end="16080064000t" region="region0" style="style0">안 돼</p>
<p xml:id="subtitle443" begin="16128779333t" end="16139123000t" region="region0" style="style0">[한숨]</p>
<p xml:id="subtitle444" begin="16150134000t" end="16176827333t" region="region0" style="style0">어차피 네가 없는 세상은<br/>나한테 어둠뿐인걸</p>
<p xml:id="subtitle445" begin="16204187999t" end="16214531666t" region="region0" style="style0">[한숨]</p>
<p xml:id="subtitle446" begin="16298615666t" end="16321972333t" region="region0" style="style0">[애잔한 음악]</p>
<p xml:id="subtitle447" begin="16712028666t" end="16723707000t" region="region0" style="style0">오, 온달?</p>
<p xml:id="subtitle448" begin="16736720000t" end="16748398333t" region="region0" style="style0">[막대를 탁 떨어뜨린다]</p>
<p xml:id="subtitle449" begin="16894210666t" end="16905889000t" region="region0" style="style0">[수정이 벅찬 숨을 내뱉는다]</p>
<p xml:id="subtitle450" begin="17186836333t" end="17196846333t" region="region0" style="style0">네가...</p>
<p xml:id="subtitle451" begin="17222538666t" end="17235885333t" region="region0" style="style0">이번에는 내가 왔다</p>
<p xml:id="subtitle452" begin="17255905333t" end="17267583666t" region="region0" style="style0">너를 만나러</p>
<p xml:id="subtitle453" begin="17322972333t" end="17333316000t" region="region0" style="style0">온달</p>
<p xml:id="subtitle454" begin="17846495333t" end="17860175666t" region="region0" style="style0">[차 문을 달칵 연다]</p>
<p xml:id="subtitle455" begin="17884199666t" end="17904553333t" region="region0" style="style0">[엔딩곡]</p>
<p xml:id="subtitle456" begin="17996311666t" end="18007990000t" region="region0" style="style0">[자동차 시동음]</p>
<p xml:id="subtitle457" begin="18016665333t" end="18036685333t" region="region0" style="style0">(내비게이션)</p>
<p xml:id="subtitle458" begin="18047696333t" end="18058040000t" region="region0" style="style0">자막: 김한나</p>
</div>
</body>
</tt>
